{
  "common": {
    "appName": "LYX",
    "tagline": "All-in-one for car workshops",
    "loading": "Loading...",
    "save": "Save",
    "cancel": "Cancel",
    "delete": "Delete",
    "edit": "Edit",
    "create": "Create",
    "search": "Search",
    "filter": "Filter",
    "export": "Export",
    "import": "Import",
    "yes": "Yes",
    "no": "No",
    "continue": "Continue",
    "back": "Back",
    "next": "Next",
    "previous": "Previous",
    "close": "Close",
    "ok": "OK",
    "confirm": "Confirm",
    "error": "Error",
    "success": "Success",
    "warning": "Warning",
    "info": "Info",
    "view": "View",
    "download": "Download",
    "upload": "Upload",
    "actions": "Actions",
    "status": "Status",
    "active": "Active",
    "inactive": "Inactive",
    "all": "All",
    "none": "None"
  },
  
  "nav": {
    "home": "Home",
    "dashboard": "Dashboard",
    "bookings": "Bookings",
    "customers": "Customers",
    "calendar": "Calendar",
    "tireHotel": "Tire Hotel",
    "coating": "Coating/Polishing",
    "marketing": "Marketing",
    "reports": "Reports",
    "analytics": "Analytics",
    "settings": "Settings",
    "team": "Team",
    "billing": "Billing",
    "profile": "Profile",
    "help": "Help",
    "logout": "Log out"
  },
  
  "auth": {
    "login": "Log in",
    "register": "Register",
    "email": "Email",
    "password": "Password",
    "confirmPassword": "Confirm password",
    "forgotPassword": "Forgot password?",
    "resetPassword": "Reset password",
    "signInWithGoogle": "Sign in with Google",
    "signInWithEmail": "Sign in with email",
    "createAccount": "Create account",
    "alreadyHaveAccount": "Already have an account?",
    "dontHaveAccount": "Don't have an account?",
    "verifyEmail": "Verify email",
    "emailVerified": "Email verified!",
    "checkEmail": "Check your email",
    "passwordReset": "Password reset",
    "loginSuccess": "Login successful",
    "logoutSuccess": "Logout successful",
    "invalidCredentials": "Invalid email or password",
    "emailInUse": "Email already in use",
    "weakPassword": "Password is too weak",
    "passwordMismatch": "Passwords don't match"
  },
  
  "booking": {
    "title": "Bookings",
    "newBooking": "New booking",
    "editBooking": "Edit booking",
    "deleteBooking": "Delete booking",
    "viewBooking": "View booking",
    "bookingDetails": "Booking details",
    "customer": "Customer",
    "service": "Service",
    "services": "Services",
    "date": "Date",
    "time": "Time",
    "duration": "Duration",
    "status": "Status",
    "notes": "Notes",
    "internalNotes": "Internal notes",
    "price": "Price",
    "paid": "Paid",
    "unpaid": "Unpaid",
    "confirmed": "Confirmed",
    "pending": "Pending",
    "cancelled": "Cancelled",
    "completed": "Completed",
    "noShow": "No show",
    "vehicle": "Vehicle",
    "registrationNumber": "Registration number",
    "selectCustomer": "Select customer",
    "selectService": "Select service",
    "selectDate": "Select date",
    "selectTime": "Select time",
    "bookingCreated": "Booking created!",
    "bookingUpdated": "Booking updated!",
    "bookingDeleted": "Booking deleted!",
    "sendConfirmation": "Send confirmation",
    "confirmationSent": "Confirmation sent!",
    "reminder": "Reminder",
    "sendReminder": "Send reminder",
    "reminderSent": "Reminder sent!"
  },
  
  "customer": {
    "title": "Customers",
    "newCustomer": "New customer",
    "editCustomer": "Edit customer",
    "deleteCustomer": "Delete customer",
    "viewCustomer": "View customer",
    "customerDetails": "Customer details",
    "firstName": "First name",
    "lastName": "Last name",
    "fullName": "Full name",
    "email": "Email",
    "phone": "Phone",
    "address": "Address",
    "city": "City",
    "postalCode": "Postal code",
    "country": "Country",
    "company": "Company",
    "orgNumber": "Organization number",
    "notes": "Notes",
    "vehicles": "Vehicles",
    "bookings": "Bookings",
    "history": "History",
    "totalSpent": "Total spent",
    "lastVisit": "Last visit",
    "customerSince": "Customer since",
    "customerCreated": "Customer created!",
    "customerUpdated": "Customer updated!",
    "customerDeleted": "Customer deleted!",
    "noCustomers": "No customers yet",
    "searchCustomers": "Search customers..."
  },
  
  "tireHotel": {
    "title": "Tire Hotel",
    "storage": "Storage",
    "search": "Search tires",
    "registration": "Registration",
    "checkIn": "Check in",
    "checkOut": "Check out",
    "storagePosition": "Storage position",
    "position": "Position",
    "customerName": "Customer name",
    "vehicleReg": "Vehicle reg.",
    "tireSize": "Tire size",
    "tireBrand": "Tire brand",
    "tireModel": "Tire model",
    "tireCount": "Tire count",
    "tireType": "Tire type",
    "summer": "Summer",
    "winter": "Winter",
    "allSeason": "All season",
    "condition": "Condition",
    "excellent": "Excellent",
    "good": "Good",
    "fair": "Fair",
    "poor": "Poor",
    "storedDate": "Stored date",
    "retrievedDate": "Retrieved date",
    "aiAnalysis": "AI analysis",
    "analyzeWithAI": "Analyze with AI",
    "analyzeImage": "Analyze image",
    "uploadImage": "Upload image",
    "treadDepth": "Tread depth",
    "aiReport": "AI report",
    "recommendation": "Recommendation",
    "needsReplacement": "Needs replacement",
    "goodCondition": "Good condition",
    "upgradeForAI": "Upgrade for AI analysis",
    "tireCheckedIn": "Tire checked in!",
    "tireCheckedOut": "Tire checked out!",
    "noTires": "No tires stored",
    "searchTires": "Search tires..."
  },
  
  "coating": {
    "title": "Coating & Polishing",
    "newCoating": "New coating",
    "editCoating": "Edit coating",
    "viewCoating": "View coating",
    "certificate": "Certificate",
    "generateCertificate": "Generate certificate",
    "downloadCertificate": "Download certificate",
    "downloadPDF": "Download PDF",
    "verifyCertificate": "Verify certificate",
    "certificateNumber": "Certificate number",
    "product": "Product",
    "productType": "Product type",
    "ceramic": "Ceramic",
    "graphene": "Graphene",
    "wax": "Wax",
    "sealant": "Sealant",
    "warranty": "Warranty",
    "warrantyYears": "{years} year warranty",
    "warrantyExpires": "Warranty expires",
    "applicationDate": "Application date",
    "nextService": "Next service",
    "maintenanceReminder": "Maintenance reminder",
    "serviceHistory": "Service history",
    "beforePhotos": "Before photos",
    "afterPhotos": "After photos",
    "coatingCreated": "Coating created!",
    "certificateGenerated": "Certificate generated!",
    "noCoatings": "No coatings registered"
  },
  
  "marketing": {
    "title": "Marketing",
    "campaigns": "Campaigns",
    "newCampaign": "New campaign",
    "editCampaign": "Edit campaign",
    "autoPublishing": "Auto-publishing",
    "socialMedia": "Social media",
    "email": "Email",
    "sms": "SMS",
    "push": "Push notifications",
    "facebook": "Facebook",
    "instagram": "Instagram",
    "linkedin": "LinkedIn",
    "twitter": "Twitter",
    "createCampaign": "Create campaign",
    "schedule": "Schedule",
    "publish": "Publish",
    "publishNow": "Publish now",
    "draft": "Draft",
    "published": "Published",
    "scheduled": "Scheduled",
    "failed": "Failed",
    "campaignName": "Campaign name",
    "campaignType": "Campaign type",
    "targetAudience": "Target audience",
    "content": "Content",
    "media": "Media",
    "scheduledDate": "Scheduled date",
    "publishedDate": "Published date",
    "reach": "Reach",
    "engagement": "Engagement",
    "clicks": "Clicks",
    "conversions": "Conversions",
    "roi": "ROI",
    "campaignCreated": "Campaign created!",
    "campaignPublished": "Campaign published!",
    "noCampaigns": "No campaigns yet"
  },
  
  "reports": {
    "title": "Reports",
    "analytics": "Analytics",
    "revenue": "Revenue",
    "bookings": "Bookings",
    "customers": "Customers",
    "services": "Services",
    "performance": "Performance",
    "period": "Period",
    "today": "Today",
    "yesterday": "Yesterday",
    "thisWeek": "This week",
    "lastWeek": "Last week",
    "thisMonth": "This month",
    "lastMonth": "Last month",
    "thisYear": "This year",
    "lastYear": "Last year",
    "custom": "Custom",
    "from": "From",
    "to": "To",
    "export": "Export",
    "exportCSV": "Export CSV",
    "exportPDF": "Export PDF",
    "print": "Print",
    "totalRevenue": "Total revenue",
    "totalBookings": "Total bookings",
    "newCustomers": "New customers",
    "averageBookingValue": "Average booking value",
    "mostPopularService": "Most popular service",
    "topCustomers": "Top customers",
    "revenueGrowth": "Revenue growth",
    "bookingTrends": "Booking trends",
    "customerRetention": "Customer retention"
  },
  
  "settings": {
    "title": "Settings",
    "general": "General",
    "organization": "Organization",
    "organizationName": "Organization name",
    "organizationDetails": "Organization details",
    "profile": "Profile",
    "profileDetails": "Profile details",
    "security": "Security",
    "billing": "Billing",
    "subscription": "Subscription",
    "notifications": "Notifications",
    "notificationSettings": "Notification settings",
    "integrations": "Integrations",
    "api": "API",
    "apiKeys": "API keys",
    "language": "Language",
    "changeLanguage": "Change language",
    "timezone": "Timezone",
    "currency": "Currency",
    "dateFormat": "Date format",
    "timeFormat": "Time format",
    "theme": "Theme",
    "darkMode": "Dark mode",
    "lightMode": "Light mode",
    "systemMode": "System",
    "appearance": "Appearance",
    "businessHours": "Business hours",
    "openingHours": "Opening hours",
    "closingHours": "Closing hours",
    "workingDays": "Working days",
    "holidays": "Holidays",
    "bookingSettings": "Booking settings",
    "serviceSettings": "Service settings",
    "emailSettings": "Email settings",
    "smsSettings": "SMS settings",
    "settingsSaved": "Settings saved!",
    "changesSaved": "Changes saved!"
  },
  
  "pricing": {
    "title": "Pricing",
    "choosePlan": "Choose plan",
    "currentPlan": "Current plan",
    "upgrade": "Upgrade",
    "downgrade": "Downgrade",
    "changePlan": "Change plan",
    "cancelSubscription": "Cancel subscription",
    "free": "Free",
    "startup": "Startup",
    "business": "Business",
    "enterprise": "Enterprise",
    "perMonth": "per month",
    "perYear": "per year",
    "billed": "Billed",
    "billedMonthly": "Billed monthly",
    "billedYearly": "Billed yearly",
    "monthly": "Monthly",
    "yearly": "Yearly",
    "save20": "Save 20%",
    "save": "Save {amount}",
    "features": "Features",
    "includedFeatures": "Included features",
    "upTo": "Up to",
    "unlimited": "Unlimited",
    "bookings": "bookings",
    "users": "users",
    "customers": "customers",
    "storage": "storage",
    "support": "Support",
    "basicSupport": "Basic support",
    "prioritySupport": "Priority support",
    "dedicatedSupport": "Dedicated support",
    "allFeatures": "All features",
    "advancedFeatures": "Advanced features",
    "customFeatures": "Custom features",
    "startFreeTrial": "Start free trial",
    "trialDays": "{days} days free trial",
    "noCardRequired": "No credit card required"
  },
  
  "errors": {
    "generic": "Something went wrong. Please try again.",
    "network": "Network error. Check your internet connection.",
    "unauthorized": "You don't have access to this resource.",
    "forbidden": "Access denied.",
    "notFound": "Page not found.",
    "validation": "Please fill in all required fields.",
    "invalidInput": "Invalid input.",
    "serverError": "Server error. Please try again later.",
    "timeout": "Request timed out. Please try again.",
    "conflictError": "Resource already exists.",
    "tooManyRequests": "Too many requests. Try again later.",
    "serviceUnavailable": "Service temporarily unavailable.",
    "unexpectedError": "An unexpected error occurred."
  },
  
  "success": {
    "saved": "Changes saved!",
    "created": "Created!",
    "updated": "Updated!",
    "deleted": "Deleted!",
    "sent": "Sent!",
    "uploaded": "Uploaded!",
    "downloaded": "Downloaded!",
    "copied": "Copied!",
    "published": "Published!",
    "scheduled": "Scheduled!",
    "cancelled": "Cancelled!",
    "completed": "Completed!",
    "confirmed": "Confirmed!",
    "verified": "Verified!",
    "approved": "Approved!",
    "rejected": "Rejected!",
    "archived": "Archived!",
    "restored": "Restored!"
  },
  
  "validation": {
    "required": "This field is required",
    "emailInvalid": "Invalid email address",
    "phoneInvalid": "Invalid phone number",
    "urlInvalid": "Invalid URL",
    "minLength": "Minimum {min} characters",
    "maxLength": "Maximum {max} characters",
    "minValue": "Minimum value is {min}",
    "maxValue": "Maximum value is {max}",
    "mustMatch": "Fields must match",
    "invalidFormat": "Invalid format",
    "invalidDate": "Invalid date",
    "dateInPast": "Date must be in the future",
    "dateInFuture": "Date must be in the past"
  },
  
  "metadata": {
    "home": {
      "title": "LYX - All-in-one for car workshops | Booking, Tire Hotel, Coating",
      "description": "Modern SaaS platform for car workshops. Booking, customer portal, tire hotel, coating certificates, marketing and reports - all in one."
    },
    "pricing": {
      "title": "Pricing - LYX | Transparent pricing for all sizes",
      "description": "Choose the right plan for your car workshop. Start free, upgrade when you need it. No hidden costs."
    },
    "features": {
      "title": "Features - LYX | Complete toolkit for car workshops",
      "description": "Booking system, customer management, tire hotel, coating certificates, AI analysis, marketing and more."
    },
    "about": {
      "title": "About LYX | Modern platform for car workshops",
      "description": "LYX is a Norwegian SaaS platform that digitizes car workshops. Created by workshop owners for workshop owners."
    },
    "contact": {
      "title": "Contact us - LYX | We'll help you get started",
      "description": "Have questions about LYX? Contact us for a demo, support or partnership."
    }
  }
}
